Bookdl/__init__.py
Bookdl/books.py
Bookdl/logger.py
Bookdl/pdfdrive.py
Bookdl/save.py
Bookdl-0.1.4.data/scripts/Bookdl
Bookdl-0.1.4.dist-info/LICENSE
Bookdl-0.1.4.dist-info/METADATA
Bookdl-0.1.4.dist-info/WHEEL
Bookdl-0.1.4.dist-info/top_level.txt
Bookdl-0.1.4.dist-info/RECORD
